talentwizer_commons/__init__.py
talentwizer_commons/app/.DS_Store
talentwizer_commons/app/__init__.py
talentwizer_commons/app/api/.DS_Store
talentwizer_commons/app/api/__init__.py
talentwizer_commons/app/api/routers/.DS_Store
talentwizer_commons/app/api/routers/__init__.py
talentwizer_commons/app/api/routers/chargebee.py
talentwizer_commons/app/api/routers/chat.py
talentwizer_commons/app/api/routers/company.py
talentwizer_commons/app/api/routers/plan.py
talentwizer_commons/app/api/routers/razorpay.py
talentwizer_commons/app/api/routers/session.py
talentwizer_commons/app/api/routers/status.py
talentwizer_commons/app/api/routers/stripe_customer_session.py
talentwizer_commons/app/api/routers/stripe_webhook.py
talentwizer_commons/app/api/routers/template.py
talentwizer_commons/app/api/routers/user.py
talentwizer_commons/app/engine/__init__.py
talentwizer_commons/app/engine/index.py
talentwizer_commons/app/engine/mongo.py
talentwizer_commons/utils/__init__.py
talentwizer_commons/utils/celery_init.py
talentwizer_commons/utils/cleanup.py
talentwizer_commons/utils/core.py
talentwizer_commons/utils/db.py
talentwizer_commons/utils/email.py
talentwizer_commons/utils/email_utils.py
talentwizer_commons/utils/exceptions.py
talentwizer_commons/utils/helper.py
talentwizer_commons/utils/llm.py
talentwizer_commons/utils/llm_utils.py
talentwizer_commons/utils/objectid.py
talentwizer_commons/utils/redis_cleanup.py
talentwizer_commons/utils/search.py
talentwizer_commons/utils/sequence_utils.py
talentwizer_commons/utils/state_manager.py
talentwizer_commons/utils/storage.py
talentwizer_commons/utils/subscription_management.py
talentwizer_commons/utils/task_restore.py
talentwizer_commons/utils/tasks.py
talentwizer_commons/utils/template_utils.py
talentwizer_commons/utils/test_utils.py
talentwizer_commons/utils/token_utils.py
talentwizer_commons-1.0.14.dist-info/METADATA
talentwizer_commons-1.0.14.dist-info/WHEEL
talentwizer_commons-1.0.14.dist-info/RECORD
