Metadata-Version: 2.1
Name: talentwizer_commons
Version: 1.0.14
Summary: Common utilities and objects for Talentwizer projects
Author: Mihir
Author-email: mail@mihir@talentwizer.com
Requires-Python: >=3.11,<3.12
Classifier: Programming Language :: Python :: 3
Classifier: Programming Language :: Python :: 3.11
Requires-Dist: aiofiles (>=23.2.1,<24.0.0)
Requires-Dist: asgiref (>=3.7.2)
Requires-Dist: boto3 (>=1.34.54,<2.0.0)
Requires-Dist: celery (>=5.2.0,<6.0.0)
Requires-Dist: chargebee (==2.47.1)
Requires-Dist: docx2txt (>=0.8,<0.9)
Requires-Dist: email-validator (>=2.1.1,<3.0.0)
Requires-Dist: fastapi (>=0.104.1,<0.105.0)
Requires-Dist: flower (>=2.0.1,<3.0.0)
Requires-Dist: google-api-python-client (>=2.92.0,<3.0.0)
Requires-Dist: google-auth (>=2.18.1,<3.0.0)
Requires-Dist: google-auth-oauthlib (>=1.0.0,<2.0.0)
Requires-Dist: linkedin_api
Requires-Dist: linkedin_scraper
Requires-Dist: llama-index (==0.10.33)
Requires-Dist: llama-index-tools-google
Requires-Dist: llama-index-vector-stores-mongodb (==0.1.4)
Requires-Dist: msal (==1.31.1)
Requires-Dist: nltk (>=3.8.1,<4.0.0)
Requires-Dist: pdfplumber (>=0.10.4,<0.11.0)
Requires-Dist: proxycurl-py
Requires-Dist: pymongo (>=4.6.1,<5.0.0)
Requires-Dist: pypdf (>=4.0.1,<5.0.0)
Requires-Dist: python-dotenv (>=1.0.0,<2.0.0)
Requires-Dist: python-multipart (>=0.0.9,<0.0.10)
Requires-Dist: redis (>=4.0.2,<5.0.0)
Requires-Dist: stripe (>=5.2.0,<6.0.0)
Requires-Dist: uvicorn[standard] (>=0.23.2,<0.24.0)
Requires-Dist: wikipedia (>=1.4.0,<2.0.0)
